makefile/__init__.py
makefile/makefile.py
makefile-1.1.0.dist-info/LICENSE
makefile-1.1.0.dist-info/METADATA
makefile-1.1.0.dist-info/WHEEL
makefile-1.1.0.dist-info/top_level.txt
makefile-1.1.0.dist-info/RECORD
